fatbeaglenoti/__init__.py
fatbeaglenoti/__main__.py
fatbeaglenoti/notify.py
fatbeagle_noti-1.2.0.dist-info/METADATA
fatbeagle_noti-1.2.0.dist-info/WHEEL
fatbeagle_noti-1.2.0.dist-info/top_level.txt
fatbeagle_noti-1.2.0.dist-info/RECORD
